metaCTD/VERSION
metaCTD/__init__.py
metaCTD/gui/__init__.py
metaCTD/gui/metaCTD_gui.py
metaCTD/ships/ships.yaml
metaCTD/stations/iow_stations.yaml
metaCTD-0.4.4.dist-info/LICENSE
metaCTD-0.4.4.dist-info/METADATA
metaCTD-0.4.4.dist-info/WHEEL
metaCTD-0.4.4.dist-info/entry_points.txt
metaCTD-0.4.4.dist-info/top_level.txt
metaCTD-0.4.4.dist-info/RECORD
