Metadata-Version: 2.1
Name: metaCTD
Version: 0.4.4
Summary: GUI to read and view conductivity, temperature and depth (CTD) files and to manage and creating metadata by defining stations, transects, campaigns
Home-page: https://github.com/MarineDataTools/metaCTD
Author: Peter Holtermann
Author-email: peter.holtermann@io-warnemuende.de
License: GPLv03
Platform: UNKNOWN
Requires-Dist: geojson
Requires-Dist: gsw
Requires-Dist: pyaml
Requires-Dist: pycnv
Requires-Dist: pyproj
Requires-Dist: pysst
Requires-Dist: pytz
